src/bloomdata-rabidgeek/__init__.py
src/bloomdata-rabidgeek/helper_functions.py
bloomdata_rabidgeek-0.0.1.dist-info/METADATA
bloomdata_rabidgeek-0.0.1.dist-info/WHEEL
bloomdata_rabidgeek-0.0.1.dist-info/licenses/LICENSE
bloomdata_rabidgeek-0.0.1.dist-info/RECORD
